api_commons/__init__.py
api_commons/common.py
api_commons/decorator.py
api_commons/dto.py
api_commons/error.py
django_api_commons-1.0.6.dist-info/DESCRIPTION.rst
django_api_commons-1.0.6.dist-info/METADATA
django_api_commons-1.0.6.dist-info/RECORD
django_api_commons-1.0.6.dist-info/WHEEL
django_api_commons-1.0.6.dist-info/metadata.json
django_api_commons-1.0.6.dist-info/top_level.txt
